flask_cache/__init__.py
flask_cache/_compat.py
flask_cache/backends.py
flask_cache/jinja2ext.py
Flask_Cache2-0.13.1.dist-info/LICENSE
Flask_Cache2-0.13.1.dist-info/METADATA
Flask_Cache2-0.13.1.dist-info/WHEEL
Flask_Cache2-0.13.1.dist-info/top_level.txt
Flask_Cache2-0.13.1.dist-info/RECORD
